configs/__init__.py
configs/config.py
configs/prompt.py
sollu-0.2.dist-info/licenses/LICENSE
sollu-0.2.dist-info/METADATA
sollu-0.2.dist-info/WHEEL
sollu-0.2.dist-info/entry_points.txt
sollu-0.2.dist-info/top_level.txt
sollu-0.2.dist-info/RECORD
