Metadata-Version: 2.4
Name: Sollu
Version: 0.2
Summary: Fetch definitions and example sentences for words directly from your terminal
Author: Ashvanth.S
License:                                  Apache License
Project-URL: Homepage, https://github.com/ash-01xor/Sollu
Classifier: Development Status :: 2 - Pre-Alpha
License-File: LICENSE
Requires-Dist: click
Requires-Dist: google-genai
Requires-Dist: pydantic
Requires-Dist: pytest
Requires-Dist: python-dotenv
Requires-Dist: rich
Provides-Extra: test
Requires-Dist: pytest; extra == "test"
Requires-Dist: pytest-mock; extra == "test"
Dynamic: license-file
